multiprocess/__init__.pyi
multiprocess/connection.pyi
multiprocess/context.pyi
multiprocess/forkserver.pyi
multiprocess/heap.pyi
multiprocess/managers.pyi
multiprocess/pool.pyi
multiprocess/popen_fork.pyi
multiprocess/popen_forkserver.pyi
multiprocess/popen_spawn_posix.pyi
multiprocess/popen_spawn_win32.pyi
multiprocess/process.pyi
multiprocess/queues.pyi
multiprocess/reduction.pyi
multiprocess/resource_sharer.pyi
multiprocess/resource_tracker.pyi
multiprocess/shared_memory.pyi
multiprocess/sharedctypes.pyi
multiprocess/spawn.pyi
multiprocess/synchronize.pyi
multiprocess/util.pyi
multiprocess/dummy/__init__.pyi
multiprocess/dummy/connection.pyi
multiprocess_stubs-0.1.0.dist-info/METADATA
multiprocess_stubs-0.1.0.dist-info/WHEEL
multiprocess_stubs-0.1.0.dist-info/licenses/LICENSE.txt
multiprocess_stubs-0.1.0.dist-info/RECORD
