Metadata-Version: 2.3
Name: multiprocess-stubs
Version: 0.1.0
Summary: Type stubs for the multiprocess library.
Project-URL: Homepage, https://github.com/zhou13/multiprocess-stub
Project-URL: Issues, https://github.com/zhou13/multiprocess-stub/issues
Author-email: Yichao Zhou <zyc@berkeley.edu>
Classifier: License :: OSI Approved :: MIT License
Classifier: Operating System :: OS Independent
Classifier: Programming Language :: Python :: 3
Requires-Python: >=3.8
Requires-Dist: multiprocess
